{
    "patches": [
        {
            "label": "2025-11-28_19-31-50",
            "content": "@@ -1541,259 +1541,4 @@\n     \n-def __init__(self):%0A        self.contacts: list%5BContact%5D = %5B%5D%0A%0A    def addContact(self, name: str, fones: list%5BFone%5D):%0A        .%0A    def getContact(self, name: str) -%3E Contact %7C None:%0A        return name%0A%0A    def rmContact(self, name: str):%0A        %0A%0A    \n",
            "lines": "59"
        },
        {
            "label": "2025-11-28_19-52-13",
            "content": "@@ -1602,221 +1602,8 @@\n = %5B%5D\n-%0A    %0A    def findPosByName(self, name: str) -%3E int:%0A        for i, contact in enumerate(self.contacts):%0A            if contact.getName == name:%0A                return i%0A            else:%0A                return -1\n %0A%0A  \n@@ -1660,24 +1660,25 @@\n %5D):%0A        \n+.\n %0A    def get\n",
            "lines": "70"
        },
        {
            "label": "2025-11-28_20-08-37",
            "content": "@@ -1881,454 +1881,124 @@\n     \n-pos = self.findPosByName(name)%0A        if pos == -1:%0A            self.contacts.append(Contact(name, fones))%0A        else:%0A            self.contacts%5Bpos%5D.fones = fones%0A%0A    def getContact(self, name: str) -%3E Contact %7C None:%0A        pos = self.findPosByName(name)%0A        if pos == -1:%0A            return None%0A        else:%0A            return self.contacts%5Bpos%5D%0A%0A    def rmContact(self, name: str):%0A        pos = self.findPosByName(name)%0A        if\n+%0A    def getContact(self, name: str) -%3E Contact %7C None:%0A        return name%0A%0A    def rmContact(self, name: str):%0A   \n     \n",
            "lines": "77"
        },
        {
            "label": "2025-11-28_20-20-16",
            "content": "class Fone:\n    def __init__(self, id: str, number: str):\n        self.id = id\n        self.number = number\n    \n    def isValid(self) -> bool:\n        valido = \"0123456789()-.\"\n        for i in self.number:\n            if i not in valido:\n                return False\n        return True\n\n    def getId(self) -> str:\n        return self.id\n    def getNumber(self) -> str:\n        return self.number\n    \n    def __str__(self) -> str:\n        return f\"{self.id}:{self.number}\"\n    \nclass Contact:\n    def __init__(self, name: str):\n        self.name = name\n        self.favorited = False\n        self.fones: list[Fone] =[] \n\n    def addFone(self, id: str, number: str) -> None:\n        fone = Fone(id, number)\n        if fone.isValid():\n            self.fones.append(fone)\n        else:\n            print(\"fail: invalid number\")\n\n    def rmFone(self, index: int) -> None:\n        if 0 <= index < len(self.fones):\n            self.fones.pop(index)\n        else:\n            print(\"fail: indice invalido\")\n    \n    def toogleFavorited(self) -> None:\n        self.favorited = not self.favorited\n    \n    def isFavorited(self) -> bool:\n        return True\n    \n    def getFones(self) -> list:\n        return self.fones\n    def getName(self) -> str:\n        return self.name\n    def setName(self, name: str) -> None:\n        self.name = name\n\n    def __str__(self) -> str:\n        fav = \"@\" if self.favorited else \"-\"\n        fones_str = \", \".join(str(f) for f in self.fones)\n        return f\"{fav} {self.name} [{fones_str}]\"\n    \nclass Agenda:\n    def __init__(self):\n        self.contacts: list[Contact] = []\n    \n    def findPosByName(self, name: str) -> int:\n        for i, contact in enumerate(self.contacts):\n            if contact.getName == name:\n                return i\n            else:\n                return -1\n\n    def addContact(self, name: str, fones: list[Fone]):\n        pos = self.findPosByName(name)\n        if pos == -1:\n            self.contacts.append(Contact(name, fones))\n        else:\n            self.contacts[pos].fones = fones\n\n    def getContact(self, name: str) -> Contact | None:\n        pos = self.findPosByName(name)\n        if pos == -1:\n            return None\n        else:\n            return self.contacts[pos]\n\n    def rmContact(self, name: str):\n        pos = self.findPosByName(name)\n        if     \n\n    ",
            "lines": "87"
        }
    ]
}